oc_connections/ConnectionManager.py
oc_connections/CredentialManager.py
oc_connections/__init__.py
oc_connections-1.0.1.dist-info/LICENSE
oc_connections-1.0.1.dist-info/METADATA
oc_connections-1.0.1.dist-info/WHEEL
oc_connections-1.0.1.dist-info/top_level.txt
oc_connections-1.0.1.dist-info/RECORD
