Metadata-Version: 2.1
Name: oc-connections
Version: 1.0.1
Summary: Connection Manages
License: Apache License 2.0
Requires-Python: >=3.6
License-File: LICENSE
Requires-Dist: oc-cdtapi
Requires-Dist: oc-pyfs
Requires-Dist: pysmb
